Metadata-Version: 2.1
Name: feather.py
Version: 0.1.0
Summary: SQLITE3 CLI wrapper build on python.
Home-page: https://github.com/sarthhh/feather
Author: sarthhh
Author-email: shiva02939@gmail.com
License: MIT
Keywords: sqlite3,sqlite,cli,database
Requires-Python: >=3.8.0
